{
	"name": "InputDataset",
	"properties": {
		"linkedServiceName": {
			"referenceName": "newAzureBlobStorage1",
			"type": "LinkedServiceReference"
		},
		"annotations": [],
		"type": "DelimitedText",
		"typeProperties": {
			"location": {
				"type": "AzureBlobStorageLocation",
				"fileName": "Google_Stock_Price_Train.csv",
				"folderPath": "input",
				"container": "newcontainer"
			},
			"columnDelimiter": ",",
			"escapeChar": "\\",
			"firstRowAsHeader": true,
			"quoteChar": "\""
		},
		"schema": [
			{
				"name": "Date",
				"type": "String"
			},
			{
				"name": "Open",
				"type": "String"
			},
			{
				"name": "High",
				"type": "String"
			},
			{
				"name": "Low",
				"type": "String"
			},
			{
				"name": "Close",
				"type": "String"
			},
			{
				"name": "Volume",
				"type": "String"
			}
		]
	},
	"type": "Microsoft.DataFactory/factories/datasets"
}